omegacli/__init__.py
omegaconf_argparse-1.0.1.dist-info/LICENSE
omegaconf_argparse-1.0.1.dist-info/WHEEL
omegaconf_argparse-1.0.1.dist-info/METADATA
omegaconf_argparse-1.0.1.dist-info/RECORD
