Metadata-Version: 2.1
Name: omegaconf-argparse
Version: 1.0.1
Summary: Integration between Omegaconf and argparse for mixed config file and CLI arguments
License: Apache-2.0
Author: Giorgos Paraskevopoulos
Author-email: georgepar.91@gmail.com
Requires-Python: >=3.7,<4.0
Classifier: License :: OSI Approved :: Apache Software License
Classifier: Programming Language :: Python :: 3
Classifier: Programming Language :: Python :: 3.7
Classifier: Programming Language :: Python :: 3.8
Classifier: Programming Language :: Python :: 3.9
Requires-Dist: omegaconf (>=2.0.6,<3.0.0)
